pytest_split_tests/__init__.py
pytest_split_tests-1.1.0.dist-info/LICENSE
pytest_split_tests-1.1.0.dist-info/METADATA
pytest_split_tests-1.1.0.dist-info/WHEEL
pytest_split_tests-1.1.0.dist-info/entry_points.txt
pytest_split_tests-1.1.0.dist-info/top_level.txt
pytest_split_tests-1.1.0.dist-info/RECORD
